algovera/__init__.py
algovera/_version.py
algovera/commands.py
algovera/jupyterfrontend.py
algovera/ocean_transaction.py
algovera/sessions.py
algovera/shell.py
algovera/widgets.py
algovera/labextension/build_log.json
algovera/labextension/package.json
algovera/labextension/schemas/algovera/package.json.orig
algovera/labextension/schemas/algovera/plugin.json
algovera/labextension/static/_4afa.358ba94cf4ce009c8966.js
algovera/labextension/static/_4afa.358ba94cf4ce009c8966.js.map
algovera/labextension/static/lib_index_js.f6621001b911755234cc.js
algovera/labextension/static/lib_index_js.f6621001b911755234cc.js.map
algovera/labextension/static/lib_plugin_js-lib_widgets_frontend_js.a98db2b17cf6b3330112.js
algovera/labextension/static/lib_plugin_js-lib_widgets_frontend_js.a98db2b17cf6b3330112.js.map
algovera/labextension/static/remoteEntry.403be3fceb1adf1a7e6a.js
algovera/labextension/static/remoteEntry.403be3fceb1adf1a7e6a.js.map
algovera/labextension/static/style.js
algovera/labextension/static/style_style_js.d00d12a32cb5898f6fb0.js
algovera/labextension/static/style_style_js.d00d12a32cb5898f6fb0.js.map
algovera/labextension/static/vendors-node_modules_css-loader_dist_runtime_api_js-node_modules_css-loader_dist_runtime_cssW-72eba1.1130b4fe5cc6c0440fed.js
algovera/labextension/static/vendors-node_modules_css-loader_dist_runtime_api_js-node_modules_css-loader_dist_runtime_cssW-72eba1.1130b4fe5cc6c0440fed.js.map
algovera/labextension/static/vendors-node_modules_ethers_lib_esm_index_js.f95e80d94e56f6362ced.js
algovera/labextension/static/vendors-node_modules_ethers_lib_esm_index_js.f95e80d94e56f6362ced.js.map
algovera/labextension/static/vendors-node_modules_jquery_dist_jquery_js.afeee86c9790c447b0a8.js
algovera/labextension/static/vendors-node_modules_jquery_dist_jquery_js.afeee86c9790c447b0a8.js.map
algovera/labextension/static/vendors-node_modules_jupyter-widgets_controls_lib_index_js.361d02ed940b95b2613e.js
algovera-0.2.0.dist-info/LICENSE
algovera-0.2.0.dist-info/METADATA
algovera-0.2.0.dist-info/WHEEL
algovera-0.2.0.dist-info/top_level.txt
algovera-0.2.0.dist-info/RECORD
